<?xml version="1.0" encoding="utf-8" ?>
<dwsync>
<file name="button_secondary.png" server="tuquinielita.com/public_html/carwash/" local="130348422160000000" remote="130375841260000000" Dst="1" />
<file name="button_secondary@2x.png" server="tuquinielita.com/public_html/carwash/" local="130348422160000000" remote="130375841260000000" Dst="1" />
<file name="button_secondary_selected.png" server="tuquinielita.com/public_html/carwash/" local="130348422160000000" remote="130375841260000000" Dst="1" />
<file name="button_secondary_selected@2x.png" server="tuquinielita.com/public_html/carwash/" local="130348422160000000" remote="130375841270000000" Dst="1" />
<file name="check.png" server="tuquinielita.com/public_html/carwash/" local="130348422160000000" remote="130375841270000000" Dst="1" />
<file name="check@2x.png" server="tuquinielita.com/public_html/carwash/" local="130348422160000000" remote="130375841280000000" Dst="1" />
<file name="ios_sample_icon.png" server="tuquinielita.com/public_html/carwash/" local="130348422160000000" remote="130375841280000000" Dst="1" />
<file name="ios_sample_icon@2x.png" server="tuquinielita.com/public_html/carwash/" local="130348422160000000" remote="130375841280000000" Dst="1" />
</dwsync>